README.rst
setup.py
lizhifm.egg-info/PKG-INFO
lizhifm.egg-info/SOURCES.txt
lizhifm.egg-info/dependency_links.txt
lizhifm.egg-info/entry_points.txt
lizhifm.egg-info/not-zip-safe
lizhifm.egg-info/requires.txt
lizhifm.egg-info/top_level.txt
src/__init__.py
src/download.py
src/each_anchor.py
src/good_anchor.py
src/hot_anchor.py
src/search_keyword.py